async_interrupt/__init__.py
async_interrupt/py.typed
async_interrupt-1.2.1.dist-info/LICENSE
async_interrupt-1.2.1.dist-info/METADATA
async_interrupt-1.2.1.dist-info/WHEEL
async_interrupt-1.2.1.dist-info/RECORD
