Metadata-Version: 2.3
Name: async_interrupt
Version: 1.2.1
Summary: Context manager to raise an exception when a future is done
License: Apache-2.0
Author: J. Nick Koston
Author-email: nick@koston.org
Requires-Python: >=3.9
Classifier: Development Status :: 5 - Production/Stable
Classifier: Intended Audience :: Developers
Classifier: License :: OSI Approved :: Apache Software License
Classifier: Natural Language :: English
Classifier: Operating System :: OS Independent
Classifier: Programming Language :: Python :: 3
Classifier: Programming Language :: Python :: 3.9
Classifier: Programming Language :: Python :: 3.10
Classifier: Programming Language :: Python :: 3.11
Classifier: Programming Language :: Python :: 3.12
Classifier: Programming Language :: Python :: 3.13
Classifier: Topic :: Software Development :: Libraries
Project-URL: Bug Tracker, https://github.com/bdraco/async_interrupt/issues
Project-URL: Changelog, https://github.com/bdraco/async_interrupt/blob/main/CHANGELOG.md
Project-URL: Repository, https://github.com/bdraco/async_interrupt
